enumerate_smiles/IO.py
enumerate_smiles/__init__.py
enumerate_smiles/main.py
enumerate_smiles/smiles_enumeration.py
enumerate_smiles-0.0.1.post1.dist-info/LICENSE
enumerate_smiles-0.0.1.post1.dist-info/METADATA
enumerate_smiles-0.0.1.post1.dist-info/WHEEL
enumerate_smiles-0.0.1.post1.dist-info/top_level.txt
enumerate_smiles-0.0.1.post1.dist-info/RECORD
